LICENSE.txt
README.md
setup.cfg
setup.py
Topsis_Shivesh_102003128/__init__.py
Topsis_Shivesh_102003128/topsis_102003128.py
Topsis_Shivesh_102003128.egg-info/PKG-INFO
Topsis_Shivesh_102003128.egg-info/SOURCES.txt
Topsis_Shivesh_102003128.egg-info/dependency_links.txt
Topsis_Shivesh_102003128.egg-info/requires.txt
Topsis_Shivesh_102003128.egg-info/top_level.txt