Metadata-Version: 2.1
Name: Topsis-Shivesh-102003128
Version: 0.1
Summary: This package is implimentation of multi-criteria decision analysis using topsis
Home-page: https://github.com/Shivi1771/Topsis-Shivesh-102003128
Download-URL: https://github.com/Shivi1771/Topsis-Shivesh-102003128/archive/refs/tags/v_01.tar.gz
Author: Shivesh Narula
Author-email: snarula_be20@thapar.edu
License: MIT
Keywords: topsis
Classifier: Development Status :: 3 - Alpha
Classifier: Intended Audience :: Developers
Classifier: Topic :: Software Development :: Build Tools
Classifier: License :: OSI Approved :: MIT License
Classifier: Programming Language :: Python :: 3
Classifier: Programming Language :: Python :: 3.4
Classifier: Programming Language :: Python :: 3.5
Classifier: Programming Language :: Python :: 3.6
License-File: LICENSE.txt
